LICENSE
README.rst
cmdstancache.py
setup.cfg
setup.py
cmdstancache.egg-info/PKG-INFO
cmdstancache.egg-info/SOURCES.txt
cmdstancache.egg-info/dependency_links.txt
cmdstancache.egg-info/requires.txt
cmdstancache.egg-info/top_level.txt